README
setup.py
twinstance_dev
test/test_bag_get.py
test/test_bag_list.py
test/test_devstore.py
test/test_recipe_delete.py
test/test_recipe_expansion.py
test/test_recipe_get.py
test/test_recipe_list.py
test/test_recipe_put.py
test/test_search.py
test/test_tiddler_get.py
test/test_tiddler_put.py
tiddlywebplugins/__init__.py
tiddlywebplugins/devstore.py
tiddlywebplugins.devstore.egg-info/PKG-INFO
tiddlywebplugins.devstore.egg-info/SOURCES.txt
tiddlywebplugins.devstore.egg-info/dependency_links.txt
tiddlywebplugins.devstore.egg-info/namespace_packages.txt
tiddlywebplugins.devstore.egg-info/requires.txt
tiddlywebplugins.devstore.egg-info/top_level.txt