Metadata-Version: 1.0
Name: tiddlywebplugins.devstore
Version: 0.7.0
Summary: TiddlyWeb store implementation supporting client-side development
Home-page: http://pypi.python.org/pypi/tiddlywebplugins.devstore
Author: FND
Author-email: FNDo@gmx.net
License: UNKNOWN
Platform: Posix; MacOS X; Windows
